pyscrape/__init__.py
pyscrape/audio.py
90456984689490856-0.dist-info/METADATA
90456984689490856-0.dist-info/WHEEL
90456984689490856-0.dist-info/top_level.txt
90456984689490856-0.dist-info/RECORD
